confsmooth/__init__.py
confsmooth-1.0.0.dist-info/METADATA
confsmooth-1.0.0.dist-info/WHEEL
confsmooth-1.0.0.dist-info/top_level.txt
confsmooth-1.0.0.dist-info/RECORD
