Metadata-Version: 2.1
Name: confsmooth
Version: 1.0.0
Summary: The algorithm smooths functions preserving local peaks. To distinguish peaks from noise it needs noise standard deviation
Home-page: https://github.com/gudasergey/confsmooth
Author: Sergey Guda
Author-email: gudasergey@yandex.ru
Maintainer: Sergey Guda
License: UNKNOWN
Platform: UNKNOWN
Classifier: Programming Language :: Python :: 3
Classifier: License :: OSI Approved :: GNU Lesser General Public License v3 or later (LGPLv3+)
Classifier: Operating System :: OS Independent
Requires-Dist: numpy (>=1.14.3)
Requires-Dist: scipy (>=1.1.0)
